{
  "executive_summary": "1. Isabelle Saporta attaque ce qu'elle appelle la technostructure qui gouverne la France. Journaliste, autrice et éditrice, habituée aux procès des lobbies agroalimentaires, elle décrit cette fois une caste administrative et politique qui se protège derrière les accusations de poujadisme ou de complotisme. L'entretien vise à rendre visible un système de reproduction, de pantouflage, de bureaucratie et de décisions verticales.\n2. L'exemple d'Édouard Philippe rejoignant le conseil d'administration d'Atos après le gouvernement lui sert à montrer la banalisation des allers-retours entre pouvoir public et grandes entreprises. Saporta ne dénonce pas seulement le montant; elle dénonce le symbole d'un rond de serviette, d'une continuité entre nomination publique, réseau privé et absence de gêne. C'est ce sentiment d'impunité qui, selon elle, rend les citoyens fous.\n3. Elle critique les agences, comités, hauts conseils et structures para-administratives qui échappent au contrôle démocratique. Le terme d'État profond est discuté, mais elle préfère finalement l'idée de métastases bureaucratiques. Ces organismes occupent de l'espace, produisent des normes, contournent le Parlement et diluent la responsabilité. Personne ne sait vraiment devant qui ils répondent.\n4. La reproduction des élites est un autre axe central. Saporta, petite-fille d'immigré, croit à la promotion républicaine mais estime qu'elle ne fonctionne plus. Les dispositifs de diversité ne changent pas l'uniformité générale des recrutements. Les jeunes de banlieue ou de la diagonale du vide restent structurellement empêchés d'accéder aux lieux de décision. Bourdieu est convoqué implicitement: la reproduction est devenue trop visible.\n5. Sa critique des écologistes municipaux n'est pas un rejet de l'écologie. Elle s'agace de gestes symboliques, de polémiques sur l'arbre de Noël ou le Tour de France, parce qu'ils donnent une image punitive ou hors-sol. Pour elle, l'écologie devrait être la matrice d'une refondation sociale, pas un marqueur de distinction pour métropoles de CSP plus.\n6. Elle décrit les grandes villes comme des bastions de classes supérieures, protégées par des murailles symboliques, servies par des petites mains mal payées et rejetées en banlieue. L'injonction anti-voiture après le Covid lui paraît aveugle aux conditions de vie de ceux qui ne peuvent pas habiter au centre. L'écologie doit donc intégrer la fracture sociale et territoriale.\n7. Saporta voit dans l'écologie une chance de refaire société, parce qu'elle touche au viscéral: manger, respirer, protéger ses enfants, vivre dans un environnement non pollué. Mais pour cela, il faut être à la hauteur: produire des politiques concrètes, accessibles, non moralisatrices et capables de réconcilier classes populaires, territoires ruraux et métropoles.\n8. Le Covid montre selon elle que tout est à portée de main lorsque les acteurs locaux contournent les procédures et mettent les mains dans le réel. Régions, villes, villages ont parfois réussi parce qu'ils ont cessé d'attendre les circuits administratifs. Remettre des sous-préfets ne suffit pas; il faudrait tirer les conséquences de cette capacité locale à agir vite.\n9. Sur agriculture et capitalisme, elle refuse les questions abstraites. L'agriculteur bio qui vend des paniers n'est pas le même capitalisme qu'une firme prédatrice. Le vrai problème est que les paysans se retrouvent parfois à gagner 400 euros par mois, enfermés par des syndicats majoritaires, la PAC, les lobbies et les choix européens. Ses livres sur l'agriculture visent précisément cette ornière.\n10. Elle critique le saupoudrage du plan de relance. Les annonces de centaines de millions deviennent faibles une fois réparties entre régions ou secteurs. On promet rénovation thermique, lycées, agriculture, mais les montants et calendriers ne transforment pas réellement. La technostructure produit de la communication plus que de la bascule.\n11. L'entretien est porté par une colère sociale, mais aussi par une demande de contre-pouvoirs. Saporta veut redonner du pouvoir au Parlement, changer le recrutement des élites, revaloriser les acteurs locaux et faire de l'écologie une matrice populaire. Elle refuse que la critique de la caste soit abandonnée aux démagogues.\n12. Les sangsues de la République, dans son propos, ne sont pas seulement des individus avides. Ce sont des mécanismes: pantouflage, agences, reproduction scolaire, verticalité, saupoudrage, mépris territorial. Pour refaire société, il faut couper ces circuits de rente et rendre l'action publique à ceux qui vivent les conséquences des décisions.",
  "youth_advice": "Le conseil aux jeunes générations est de ne pas laisser la République être confisquée par les circuits de reproduction. Saporta invite à regarder les conseils d'administration, les agences, les concours, les lobbies agricoles, les montants réels des plans et les territoires oubliés. L'écologie peut refaire société si elle parle à ceux qui mangent, travaillent, respirent et se déplacent, pas seulement aux centres-villes diplômés.",
  "reading_recommendations": [
    "Isabelle Saporta, Les Sangsues de la République",
    "Isabelle Saporta, Le Livre noir de l'agriculture",
    "Isabelle Saporta, Foutez-nous la paix",
    "Pierre Bourdieu, La Noblesse d'État",
    "Rapports sur PAC, FNSEA et politiques agricoles françaises"
  ],
  "sections": [
    {
      "title": "1. Technostructure",
      "paragraphs": [
        "Saporta attaque une caste administrative.",
        "La critique est disqualifiée comme populiste."
      ]
    },
    {
      "title": "2. Pantouflage",
      "paragraphs": [
        "Atos symbolise les allers-retours public-privé.",
        "L'impunité nourrit la colère."
      ]
    },
    {
      "title": "3. Agences",
      "paragraphs": [
        "Les structures parallèles diluent la responsabilité.",
        "Le Parlement est contourné."
      ]
    },
    {
      "title": "4. Élites",
      "paragraphs": [
        "La promotion républicaine ne fonctionne plus.",
        "La diversité reste souvent cosmétique."
      ]
    },
    {
      "title": "5. Écologie",
      "paragraphs": [
        "Elle critique les symboles hors-sol.",
        "Elle défend l'écologie comme matrice sociale."
      ]
    },
    {
      "title": "6. Métropoles",
      "paragraphs": [
        "Les centres riches rejettent les petites mains.",
        "L'anti-voiture peut être socialement aveugle."
      ]
    },
    {
      "title": "7. Refaire société",
      "paragraphs": [
        "L'écologie touche au viscéral.",
        "Elle doit parler aux classes populaires."
      ]
    },
    {
      "title": "8. Covid local",
      "paragraphs": [
        "Les acteurs locaux ont su agir vite.",
        "Les procédures centrales ont montré leurs limites."
      ]
    },
    {
      "title": "9. Agriculture",
      "paragraphs": [
        "Les paysans sont enfermés dans des circuits de pouvoir.",
        "La question n'est pas capitalisme abstrait mais rente concrète."
      ]
    },
    {
      "title": "10. Relance",
      "paragraphs": [
        "Les montants annoncés deviennent du saupoudrage.",
        "La communication masque la faiblesse réelle."
      ]
    },
    {
      "title": "11. Contre-pouvoirs",
      "paragraphs": [
        "Saporta veut Parlement et acteurs locaux renforcés.",
        "La critique de caste ne doit pas être démagogique."
      ]
    },
    {
      "title": "12. République",
      "paragraphs": [
        "Les sangsues sont des mécanismes de rente.",
        "Refaire société suppose de couper ces circuits."
      ]
    }
  ],
  "method_note": "Résumé éditorial généré depuis le transcript local data/transcripts/4DJkr2whd5g.fr-orig.vtt. Le texte suit l'ordre de l'entretien et privilégie la paraphrase afin de ne pas inventer de faits absents de la source.",
  "confidence": 0.88,
  "generated_at": "2026-06-06T23:05:00.000Z"
}